jnp3/__init__.py
jnp3/dict.py
jnp3/misc.py
jnp3/path.py
jnp3/gui/__init__.py
jnp3/gui/_compat.py
jnp3/gui/icon.py
jnp3/gui/misc.py
jnp3/gui/thread.py
jnp3/gui/widgets/CheckUpdateButton.py
jnp3/gui/widgets/DebugOutputButton.py
jnp3/gui/widgets/StyleComboBox.py
jnp3/gui/widgets/__init__.py
jnp3/gui/widgets/buttons.py
jnp3/gui/widgets/cards.py
jnp3/gui/widgets/lines.py
jnp3-0.5.2.dist-info/LICENSE
jnp3-0.5.2.dist-info/METADATA
jnp3-0.5.2.dist-info/WHEEL
jnp3-0.5.2.dist-info/top_level.txt
jnp3-0.5.2.dist-info/RECORD
