Metadata-Version: 2.1
Name: jnp3
Version: 0.5.2
Summary: 一个 Python 语言的辅助工具集
Author-email: Julian Freeman <freemanjulian372@gmail.com>
Project-URL: Homepage, https://github.com/JulianFreeman/jnp3
Project-URL: Repository, https://github.com/JulianFreeman/jnp3.git
Project-URL: Changelog, https://github.com/JulianFreeman/jnp3/blob/main/CHANGELOG.md
Classifier: License :: OSI Approved :: MIT License
Classifier: Operating System :: OS Independent
Classifier: Programming Language :: Python :: 3
Requires-Python: >=3.10
License-File: LICENSE
Provides-Extra: gui2
Requires-Dist: PySide2 ==5.15.2.1 ; extra == 'gui2'
Requires-Dist: requests ; extra == 'gui2'
Provides-Extra: gui6
Requires-Dist: PySide6-Essentials ==6.5.2 ; extra == 'gui6'
Requires-Dist: requests ; extra == 'gui6'
